{
  "coord": {
    "lon": -1.8795,
    "lat": 50.7205
  },
  "weather": [
    {
      "id": 701,
      "main": "Mist",
      "description": "mist",
      "icon": "50n"
    }
  ],
  "base": "stations",
  "main": {
    "temp": 8.86,
    "feels_like": 4.75,
    "temp_min": 8.41,
    "temp_max": 9.34,
    "pressure": 1007,
    "humidity": 93,
    "sea_level": 1007,
    "grnd_level": 1004
  },
  "visibility": 4000,
  "wind": {
    "speed": 9.77,
    "deg": 200,
    "gust": 14.92
  },
  "clouds": {
    "all": 75
  },
  "dt": 1768148978,
  "sys": {
    "type": 2,
    "id": 2082605,
    "country": "GB",
    "sunrise": 1768118755,
    "sunset": 1768148663
  },
  "timezone": 0,
  "id": 2655095,
  "name": "Bournemouth",
  "cod": 200,
  "_last_updated_utc": "2026-01-11T16:29:38.094Z"
}