{
  "coord": {
    "lon": -1.8795,
    "lat": 50.7205
  },
  "weather": [
    {
      "id": 804,
      "main": "Clouds",
      "description": "overcast clouds",
      "icon": "04n"
    }
  ],
  "base": "stations",
  "main": {
    "temp": 8.78,
    "feels_like": 8.78,
    "temp_min": 8.41,
    "temp_max": 8.98,
    "pressure": 1023,
    "humidity": 95,
    "sea_level": 1023,
    "grnd_level": 1021
  },
  "visibility": 10000,
  "wind": {
    "speed": 0.89,
    "deg": 49,
    "gust": 2.24
  },
  "clouds": {
    "all": 100
  },
  "dt": 1772937166,
  "sys": {
    "type": 2,
    "id": 2082605,
    "country": "GB",
    "sunrise": 1772951840,
    "sunset": 1772992778
  },
  "timezone": 0,
  "id": 2655095,
  "name": "Bournemouth",
  "cod": 200,
  "_last_updated_utc": "2026-03-08T02:32:50.097Z"
}