{
  "coord": {
    "lon": -1.8795,
    "lat": 50.7205
  },
  "weather": [
    {
      "id": 801,
      "main": "Clouds",
      "description": "few clouds",
      "icon": "02d"
    }
  ],
  "base": "stations",
  "main": {
    "temp": 19.87,
    "feels_like": 19.82,
    "temp_min": 19.87,
    "temp_max": 19.87,
    "pressure": 1028,
    "humidity": 73,
    "sea_level": 1028,
    "grnd_level": 1026
  },
  "visibility": 10000,
  "wind": {
    "speed": 3.28,
    "deg": 295,
    "gust": 3.61
  },
  "clouds": {
    "all": 20
  },
  "dt": 1779548549,
  "sys": {
    "type": 2,
    "id": 2037678,
    "country": "GB",
    "sunrise": 1779509330,
    "sunset": 1779566399
  },
  "timezone": 3600,
  "id": 2655095,
  "name": "Bournemouth",
  "cod": 200,
  "_last_updated_utc": "2026-05-23T15:04:01.675Z"
}