{
  "coord": {
    "lon": -1.8795,
    "lat": 50.7205
  },
  "weather": [
    {
      "id": 801,
      "main": "Clouds",
      "description": "few clouds",
      "icon": "02d"
    }
  ],
  "base": "stations",
  "main": {
    "temp": 27.73,
    "feels_like": 29.37,
    "temp_min": 25.46,
    "temp_max": 30.08,
    "pressure": 1016,
    "humidity": 63,
    "sea_level": 1016,
    "grnd_level": 1014
  },
  "visibility": 10000,
  "wind": {
    "speed": 2.24,
    "deg": 199,
    "gust": 4.47
  },
  "clouds": {
    "all": 21
  },
  "dt": 1782475761,
  "sys": {
    "type": 2,
    "id": 2082605,
    "country": "GB",
    "sunrise": 1782446156,
    "sunset": 1782505473
  },
  "timezone": 3600,
  "id": 2655095,
  "name": "Bournemouth",
  "cod": 200,
  "_last_updated_utc": "2026-06-26T12:13:26.456Z"
}