{
  "coord": {
    "lon": -1.8795,
    "lat": 50.7205
  },
  "weather": [
    {
      "id": 801,
      "main": "Clouds",
      "description": "few clouds",
      "icon": "02d"
    }
  ],
  "base": "stations",
  "main": {
    "temp": 17.93,
    "feels_like": 17.14,
    "temp_min": 15.98,
    "temp_max": 17.93,
    "pressure": 1015,
    "humidity": 52,
    "sea_level": 1015,
    "grnd_level": 1013
  },
  "visibility": 10000,
  "wind": {
    "speed": 1.54,
    "deg": 60
  },
  "clouds": {
    "all": 20
  },
  "dt": 1778353715,
  "sys": {
    "type": 1,
    "id": 1401,
    "country": "GB",
    "sunrise": 1778300894,
    "sunset": 1778355583
  },
  "timezone": 3600,
  "id": 2655095,
  "name": "Bournemouth",
  "cod": 200,
  "_last_updated_utc": "2026-05-09T19:08:35.473Z"
}