{
  "coord": {
    "lon": -1.8795,
    "lat": 50.7205
  },
  "weather": [
    {
      "id": 801,
      "main": "Clouds",
      "description": "few clouds",
      "icon": "02n"
    }
  ],
  "base": "stations",
  "main": {
    "temp": 7.9,
    "feels_like": 6.28,
    "temp_min": 6.93,
    "temp_max": 8.76,
    "pressure": 1019,
    "humidity": 74,
    "sea_level": 1019,
    "grnd_level": 1018
  },
  "visibility": 10000,
  "wind": {
    "speed": 2.57,
    "deg": 250
  },
  "clouds": {
    "all": 20
  },
  "dt": 1773261489,
  "sys": {
    "type": 2,
    "id": 2082605,
    "country": "GB",
    "sunrise": 1773210645,
    "sunset": 1773252277
  },
  "timezone": 0,
  "id": 2655095,
  "name": "Bournemouth",
  "cod": 200,
  "_last_updated_utc": "2026-03-11T20:38:09.479Z"
}