{
  "coord": {
    "lon": -1.8795,
    "lat": 50.7205
  },
  "weather": [
    {
      "id": 804,
      "main": "Clouds",
      "description": "overcast clouds",
      "icon": "04n"
    }
  ],
  "base": "stations",
  "main": {
    "temp": 7.5,
    "feels_like": 3.92,
    "temp_min": 6.19,
    "temp_max": 7.87,
    "pressure": 1011,
    "humidity": 89,
    "sea_level": 1011,
    "grnd_level": 1010
  },
  "visibility": 10000,
  "wind": {
    "speed": 6.42,
    "deg": 255,
    "gust": 12.4
  },
  "clouds": {
    "all": 100
  },
  "dt": 1766115492,
  "sys": {
    "type": 2,
    "id": 2082605,
    "country": "GB",
    "sunrise": 1766131552,
    "sunset": 1766160207
  },
  "timezone": 0,
  "id": 2655095,
  "name": "Bournemouth",
  "cod": 200,
  "_last_updated_utc": "2025-12-19T03:38:13.027Z"
}