{
  "coord": {
    "lon": -1.8795,
    "lat": 50.7205
  },
  "weather": [
    {
      "id": 802,
      "main": "Clouds",
      "description": "scattered clouds",
      "icon": "03n"
    }
  ],
  "base": "stations",
  "main": {
    "temp": 8.89,
    "feels_like": 7.46,
    "temp_min": 7.89,
    "temp_max": 9.34,
    "pressure": 1000,
    "humidity": 94,
    "sea_level": 1000,
    "grnd_level": 997
  },
  "visibility": 10000,
  "wind": {
    "speed": 2.57,
    "deg": 200
  },
  "clouds": {
    "all": 40
  },
  "dt": 1770503440,
  "sys": {
    "type": 2,
    "id": 2082605,
    "country": "GB",
    "sunrise": 1770449654,
    "sunset": 1770484146
  },
  "timezone": 0,
  "id": 2655095,
  "name": "Bournemouth",
  "cod": 200,
  "_last_updated_utc": "2026-02-07T22:30:40.167Z"
}