{
  "coord": {
    "lon": -1.8795,
    "lat": 50.7205
  },
  "weather": [
    {
      "id": 802,
      "main": "Clouds",
      "description": "scattered clouds",
      "icon": "03n"
    }
  ],
  "base": "stations",
  "main": {
    "temp": 8.73,
    "feels_like": 7.9,
    "temp_min": 7.86,
    "temp_max": 10.43,
    "pressure": 1022,
    "humidity": 87,
    "sea_level": 1022,
    "grnd_level": 1020
  },
  "visibility": 10000,
  "wind": {
    "speed": 1.79,
    "deg": 166,
    "gust": 4.02
  },
  "clouds": {
    "all": 32
  },
  "dt": 1765687127,
  "sys": {
    "type": 2,
    "id": 2082605,
    "country": "GB",
    "sunrise": 1765699332,
    "sunset": 1765728143
  },
  "timezone": 0,
  "id": 2655095,
  "name": "Bournemouth",
  "cod": 200,
  "_last_updated_utc": "2025-12-14T04:38:47.647Z"
}