{
  "coord": {
    "lon": -1.8795,
    "lat": 50.7205
  },
  "weather": [
    {
      "id": 800,
      "main": "Clear",
      "description": "clear sky",
      "icon": "01n"
    }
  ],
  "base": "stations",
  "main": {
    "temp": 11.86,
    "feels_like": 11.35,
    "temp_min": 11.86,
    "temp_max": 11.86,
    "pressure": 1015,
    "humidity": 86,
    "sea_level": 1015,
    "grnd_level": 1014
  },
  "visibility": 10000,
  "wind": {
    "speed": 8.02,
    "deg": 235,
    "gust": 13.76
  },
  "clouds": {
    "all": 0
  },
  "dt": 1776281022,
  "sys": {
    "country": "GB",
    "sunrise": 1776230007,
    "sunset": 1776279678
  },
  "timezone": 3600,
  "id": 2655095,
  "name": "Bournemouth",
  "cod": 200,
  "_last_updated_utc": "2026-04-15T19:23:42.455Z"
}